etao_ds_langchain/__init__.py
etao_ds_langchain/text_splitter.py
etao_ds_langchain/agents/__init__.py
etao_ds_langchain/agents/chatglm_functions_agent/__init__.py
etao_ds_langchain/agents/chatglm_functions_agent/base.py
etao_ds_langchain/agents/chatglm_functions_agent/output_parser.py
etao_ds_langchain/agents/chatglm_functions_agent/prompt.py
etao_ds_langchain/agents/llm_functions_agent/__init__.py
etao_ds_langchain/agents/llm_functions_agent/base.py
etao_ds_langchain/autogen_role/__init__.py
etao_ds_langchain/autogen_role/assistant.py
etao_ds_langchain/autogen_role/custom.py
etao_ds_langchain/autogen_role/groupchat_manager.py
etao_ds_langchain/autogen_role/user.py
etao_ds_langchain/chains/__init__.py
etao_ds_langchain/chains/loader_output.py
etao_ds_langchain/chains/transform.py
etao_ds_langchain/chains/autogen/__init__.py
etao_ds_langchain/chains/autogen/auto_gen.py
etao_ds_langchain/chains/combine_documents/__init__.py
etao_ds_langchain/chains/combine_documents/stuff.py
etao_ds_langchain/chains/conversational_retrieval/__init__.py
etao_ds_langchain/chains/conversational_retrieval/base.py
etao_ds_langchain/chains/question_answering/__init__.py
etao_ds_langchain/chains/retrieval/__init__.py
etao_ds_langchain/chains/retrieval/retrieval_chain.py
etao_ds_langchain/chains/router/__init__.py
etao_ds_langchain/chains/router/multi_rule.py
etao_ds_langchain/chains/router/rule_router.py
etao_ds_langchain/chat_models/__init__.py
etao_ds_langchain/chat_models/host_llm.py
etao_ds_langchain/chat_models/minimax.py
etao_ds_langchain/chat_models/proxy_llm.py
etao_ds_langchain/chat_models/qwen.py
etao_ds_langchain/chat_models/sensetime.py
etao_ds_langchain/chat_models/wenxin.py
etao_ds_langchain/chat_models/xunfeiai.py
etao_ds_langchain/chat_models/zhipuai.py
etao_ds_langchain/chat_models/interface/__init__.py
etao_ds_langchain/chat_models/interface/minimax.py
etao_ds_langchain/chat_models/interface/openai.py
etao_ds_langchain/chat_models/interface/types.py
etao_ds_langchain-0.1.13.dist-info/LICENSE
etao_ds_langchain-0.1.13.dist-info/METADATA
etao_ds_langchain-0.1.13.dist-info/WHEEL
etao_ds_langchain-0.1.13.dist-info/top_level.txt
etao_ds_langchain-0.1.13.dist-info/RECORD
