Metadata-Version: 2.1
Name: etao-ds-langchain
Version: 0.1.13
Summary: etao_ds_langchain
Home-page: UNKNOWN
Author: HaiLong Zheng
Author-email: xxxx@gmail.com
License: MIT
Platform: UNKNOWN
Classifier: License :: OSI Approved :: MIT License
Classifier: Programming Language :: Python
Classifier: Programming Language :: Python :: 3
Classifier: Programming Language :: Python :: 3.6
Classifier: Programming Language :: Python :: Implementation :: CPython
Classifier: Programming Language :: Python :: Implementation :: PyPy
Requires-Python: >=3.10.0
License-File: LICENSE
